README.md
setup.py
sakform/__init__.py
sakstig/__init__.py
sakstig/ast.py
sakstig/ast_base_types.py
sakstig/grammar.py
sakstig/ops.py
sakstig/queryset.py
sakstig/typeinfo.py
sakstig.egg-info/PKG-INFO
sakstig.egg-info/SOURCES.txt
sakstig.egg-info/dependency_links.txt
sakstig.egg-info/entry_points.txt
sakstig.egg-info/requires.txt
sakstig.egg-info/top_level.txt
sakstig/functions/__init__.py
sakstig/functions/arithmetic.py
sakstig/functions/array.py
sakstig/functions/cast.py
sakstig/functions/dictionary.py
sakstig/functions/misc.py
sakstig/functions/string.py
sakstig/functions/time.py
tests/__init__.py
tests/test_ObjectPath.py
tests/test_SakStig.py