Metadata-Version: 1.0
Name: sakstig
Version: 0.1.7
Summary: SakStig is an objectpath implementation that uses proper querysets and supports querying any python object that supports the dict or list interfaces.
Home-page: https://github.com/innovationgarage/sakstig
Author: Egil Moeller
Author-email: egil@innovationgarage.no
License: UNKNOWN
Platform: UNKNOWN
